sphinxcontrib/repl/__init__.py
sphinxcontrib/repl/mpl_backend.py
sphinxcontrib_repl-0.4.1.dist-info/LICENSE
sphinxcontrib_repl-0.4.1.dist-info/METADATA
sphinxcontrib_repl-0.4.1.dist-info/WHEEL
sphinxcontrib_repl-0.4.1.dist-info/top_level.txt
sphinxcontrib_repl-0.4.1.dist-info/RECORD
