Metadata-Version: 2.1
Name: sphinxcontrib-repl
Version: 0.4.1
Summary: Sphinx Extension - Directives to auto-evaluate Python code-blocks
Author-email: Takeshi Ikuma <tikuma@lsuhsc.edu>
License: GPL-2.0 License
Project-URL: Repository, https://github.com/sphinx-contrib/repl
Project-URL: Discussions, https://github.com/sphinx-contrib/repl/discussions
Project-URL: Issues, https://github.com/sphinx-contrib/repl/issues
Project-URL: PullRequests, https://github.com/sphinx-contrib/repl/pulls
Keywords: sphinx,autoeval,doctest-block
Classifier: Development Status :: 4 - Beta
Classifier: Environment :: Console
Classifier: Framework :: Sphinx :: Extension
Classifier: Intended Audience :: Developers
Classifier: License :: OSI Approved :: GNU General Public License v2 (GPLv2)
Classifier: Operating System :: OS Independent
Classifier: Programming Language :: Python
Classifier: Programming Language :: Python :: 3
Classifier: Topic :: Documentation
Classifier: Topic :: Documentation :: Sphinx
Classifier: Topic :: Utilities
Requires-Python: >=3.7
License-File: LICENSE
Requires-Dist: docutils
Provides-Extra: mpl
Requires-Dist: matplotlib ; extra == 'mpl'
